wp_cli/__init__.py
wp_cli/admin.py
wp_cli/cache_add.py
wp_cli/cache_decr.py
wp_cli/cache_decr_incr.py
wp_cli/cache_delete.py
wp_cli/cache_flush.py
wp_cli/cache_get.py
wp_cli/cache_incr.py
wp_cli/cache_replace.py
wp_cli/cache_set.py
wp_cli/cache_type.py
wp_cli/cap.py
wp_cli/cap_add.py
wp_cli/command.py
wp_cli/config.py
wp_cli/db_check.py
wp_cli/db_columns.py
wp_cli/db_export.py
wp_cli/db_import.py
wp_cli/db_items.py
wp_cli/db_prefix.py
wp_cli/db_query.py
wp_cli/db_search.py
wp_cli/db_tables.py
wp_cli/eval.py
wp_cli/option_add.py
wp_cli/option_add_update.py
wp_cli/option_get.py
wp_cli/option_update.py
wp_cli/post_get.py
wp_cli/post_update.py
wp_cli/search_replace.py
wp_cli/wp.py
wp_cli-0.0.1.dist-info/LICENSE
wp_cli-0.0.1.dist-info/METADATA
wp_cli-0.0.1.dist-info/WHEEL
wp_cli-0.0.1.dist-info/top_level.txt
wp_cli-0.0.1.dist-info/RECORD
